chattr/__init__.py
chattr/__main__.py
chattr/app/__init__.py
chattr/app/builder.py
chattr/app/gui.py
chattr/app/runner.py
chattr/app/settings.py
chattr/app/state.py
chattr/app/utils.py
chattr-0.0.39.dist-info/WHEEL
chattr-0.0.39.dist-info/entry_points.txt
chattr-0.0.39.dist-info/METADATA
chattr-0.0.39.dist-info/RECORD
