Metadata-Version: 2.3
Name: chattr
Version: 0.0.39
Summary: App part of the Chatacter Backend
Author: Mohamed Hisham Abdelzaher
Author-email: Mohamed Hisham Abdelzaher <mohamed.hisham.abdelzaher@gmail.com>
Requires-Dist: fastembed>=0.7.3
Requires-Dist: gradio>=5.48.0
Requires-Dist: langchain-community>=0.3.30
Requires-Dist: langchain-mcp-adapters>=0.1.10
Requires-Dist: langchain-openai>=0.3.34
Requires-Dist: langgraph>=0.6.8
Requires-Dist: loguru>=0.7.3
Requires-Dist: m3u8>=6.0.0
Requires-Dist: mem0ai>=0.1.118
Requires-Python: >=3.13.7, <3.14
